whisperx/SubtitlesProcessor.py
whisperx/__init__.py
whisperx/__main__.py
whisperx/alignment.py
whisperx/asr.py
whisperx/audio.py
whisperx/conjunctions.py
whisperx/diarize.py
whisperx/log_utils.py
whisperx/schema.py
whisperx/transcribe.py
whisperx/utils.py
whisperx/assets/mel_filters.npz
whisperx/assets/pytorch_model.bin
whisperx/vads/__init__.py
whisperx/vads/pyannote.py
whisperx/vads/silero.py
whisperx/vads/vad.py
whisperx-3.7.3.dist-info/licenses/LICENSE
whisperx-3.7.3.dist-info/METADATA
whisperx-3.7.3.dist-info/WHEEL
whisperx-3.7.3.dist-info/entry_points.txt
whisperx-3.7.3.dist-info/top_level.txt
whisperx-3.7.3.dist-info/RECORD
