Metadata-Version: 2.4
Name: whisperx
Version: 3.7.3
Summary: Time-Accurate Automatic Speech Recognition using Whisper.
Author: Max Bain
License: BSD-2-Clause
Project-URL: repository, https://github.com/m-bain/whisperx
Requires-Python: <3.14,>=3.9
License-File: LICENSE
Requires-Dist: ctranslate2>=4.5.0
Requires-Dist: faster-whisper>=1.1.1
Requires-Dist: nltk>=3.9.1
Requires-Dist: numpy<2.1.0,>=2.0.2; python_version < "3.13"
Requires-Dist: onnxruntime<1.20.0,>=1.19; python_version < "3.10"
Requires-Dist: pandas<2.3.0,>=2.2.3
Requires-Dist: av<16.0.0
Requires-Dist: numpy<2.3.0,>=2.1.0; python_version >= "3.13"
Requires-Dist: pyannote-audio<4.0.0,>=3.3.2
Requires-Dist: torch~=2.7.1
Requires-Dist: torchaudio~=2.7.1
Requires-Dist: transformers>=4.48.0
Requires-Dist: triton>=3.3.0; sys_platform == "linux" and platform_machine == "x86_64"
Dynamic: license-file
